LICENSE
README.md
setup.cfg
setup.py
neo4ia/__init__.py
neo4ia/funcs.py
neo4ia.egg-info/PKG-INFO
neo4ia.egg-info/SOURCES.txt
neo4ia.egg-info/dependency_links.txt
neo4ia.egg-info/requires.txt
neo4ia.egg-info/top_level.txt