Metadata-Version: 2.1
Name: neo4ia
Version: 1.0.0
Summary: Text processing library for languages Turkish and English
Home-page: https://github.com/taylangezici/neo4ia
Author: Taylan Gezici
Author-email: taylangezici@gmail.com
License: MIT
Download-URL: https://github.com/taylangezici/neo4ia/archive/refs/tags/v1.0.0.tar.gz
Keywords: none
Platform: UNKNOWN
Classifier: Development Status :: 3 - Alpha
Classifier: Intended Audience :: Developers
Classifier: Topic :: Software Development :: Build Tools
Classifier: License :: OSI Approved :: MIT License
Classifier: Programming Language :: Python :: 3
Classifier: Programming Language :: Python :: 3.4
Classifier: Programming Language :: Python :: 3.5
Classifier: Programming Language :: Python :: 3.6
License-File: LICENSE
